glitter/__init__.py
glitter/admin.py
glitter/apps.py
glitter/block_admin.py
glitter/block_views.py
glitter/columns.py
glitter/exceptions.py
glitter/fields.py
glitter/forms.py
glitter/integration.py
glitter/layouts.py
glitter/managers.py
glitter/middleware.py
glitter/mixins.py
glitter/models.py
glitter/page.py
glitter/signals.py
glitter/templates.py
glitter/urls.py
glitter/utils.py
glitter/views.py
glitter/widgets.py
glitter/assets/__init__.py
glitter/assets/admin.py
glitter/assets/apps.py
glitter/assets/fields.py
glitter/assets/forms.py
glitter/assets/listeners.py
glitter/assets/mixins.py
glitter/assets/models.py
glitter/assets/tests.py
glitter/assets/widgets.py
glitter/assets/migrations/0001_initial.py
glitter/assets/migrations/0002_image_category_field_optional.py
glitter/assets/migrations/__init__.py
glitter/blockadmin/__init__.py
glitter/blockadmin/blocks.py
glitter/blocks/__init__.py
glitter/blocks/banner/__init__.py
glitter/blocks/banner/admin.py
glitter/blocks/banner/apps.py
glitter/blocks/banner/models.py
glitter/blocks/banner/tests.py
glitter/blocks/banner/views.py
glitter/blocks/banner/migrations/0001_initial.py
glitter/blocks/banner/migrations/0002_linkfield.py
glitter/blocks/banner/migrations/0003_make_banner_link_optional.py
glitter/blocks/banner/migrations/0004_delete_empty_blocks.py
glitter/blocks/banner/migrations/0005_inline_position.py
glitter/blocks/banner/migrations/__init__.py
glitter/blocks/banner/templates/glitter/blocks/bannerblock.html
glitter/blocks/banner/templates/glitter/blocks/bannerblock_content.html
glitter/blocks/call_to_action/__init__.py
glitter/blocks/call_to_action/admin.py
glitter/blocks/call_to_action/apps.py
glitter/blocks/call_to_action/models.py
glitter/blocks/call_to_action/migrations/0001_initial.py
glitter/blocks/call_to_action/migrations/0002_linkfield.py
glitter/blocks/call_to_action/migrations/0003_delete_empty_blocks.py
glitter/blocks/call_to_action/migrations/__init__.py
django_glitter-0.2.10.dist-info/LICENSE
django_glitter-0.2.10.dist-info/METADATA
django_glitter-0.2.10.dist-info/WHEEL
django_glitter-0.2.10.dist-info/top_level.txt
django_glitter-0.2.10.dist-info/RECORD
