Metadata-Version: 2.1
Name: django-glitter
Version: 0.2.10
Summary: Glitter for Django
Home-page: https://github.com/developersociety/django-glitter
Maintainer: The Developer Society
Maintainer-email: studio@dev.ngo
License: BSD
Platform: any
Classifier: Environment :: Web Environment
Classifier: Framework :: Django
Classifier: Framework :: Django :: 1.8
Classifier: License :: OSI Approved :: BSD License
Classifier: Operating System :: OS Independent
Classifier: Programming Language :: Python
Classifier: Programming Language :: Python :: 2.7
Classifier: Programming Language :: Python :: 3.4
Classifier: Programming Language :: Python :: 3.5
Requires-Dist: Django (<1.10,>=1.8)
Requires-Dist: django-mptt (>=0.7)
Requires-Dist: django-mptt-admin (>=0.3)
Requires-Dist: sorl-thumbnail (>=12.2)
Requires-Dist: django-taggit (>=0.21.3)
Requires-Dist: python-dateutil (>=2.6.0)
